agent_gpt/__init__.py
agent_gpt/cli.py
agent_gpt/cli_deprecated.py
agent_gpt/core.py
agent_gpt/entrypoint.py
agent_gpt/gpt_api.py
agent_gpt/help_config.yaml
agent_gpt/simulation.py
agent_gpt/config/__init__.py
agent_gpt/config/hyperparams.py
agent_gpt/config/sagemaker.py
agent_gpt/env_host/__init__.py
agent_gpt/env_host/env_api.py
agent_gpt/env_host/server.py
agent_gpt/utils/__init__.py
agent_gpt/utils/config_utils.py
agent_gpt/utils/conversion_utils.py
agent_gpt/wrappers/__init__.py
agent_gpt/wrappers/custom_env.py
agent_gpt/wrappers/gym_env.py
agent_gpt/wrappers/unity_env.py
tests/__init__.py
tests/agent_gpt_gym_tester.py
tutorials/__init__.py
agent_gpt_aws-0.9.5.dist-info/METADATA
agent_gpt_aws-0.9.5.dist-info/WHEEL
agent_gpt_aws-0.9.5.dist-info/entry_points.txt
agent_gpt_aws-0.9.5.dist-info/top_level.txt
agent_gpt_aws-0.9.5.dist-info/RECORD
