Metadata-Version: 2.2
Name: agent-gpt-aws
Version: 0.9.5
Summary: AgentGPT CLI for training and inference on AWS SageMaker
Home-page: https://github.com/ccnets-team/agent-gpt
Author: JunHo Park
Author-email: junho@ccnets.org
License: Dual Licensed (AGENT GPT COMMERCIAL LICENSE or GNU GPLv3)
Keywords: agent gpt reinforcement-learning sagemaker
Classifier: Programming Language :: Python :: 3
Classifier: License :: OSI Approved :: GNU General Public License v3 (GPLv3)
Classifier: License :: Other/Proprietary License
Classifier: Operating System :: OS Independent
Requires-Python: >=3.8
Requires-Dist: msgpack
Requires-Dist: uvicorn
Requires-Dist: fastapi
Requires-Dist: requests
Requires-Dist: gymnasium>=1.0.0
Requires-Dist: gymnasium[mujoco]
Requires-Dist: typer
Requires-Dist: websocket-client
Requires-Dist: pyyaml
Requires-Dist: boto3
Requires-Dist: sagemaker
Provides-Extra: mujoco
Requires-Dist: gymnasium[mujoco]; extra == "mujoco"
Provides-Extra: mlagents
Requires-Dist: mlagents_envs==0.30.0; extra == "mlagents"
Requires-Dist: protobuf==3.20.0; extra == "mlagents"
Dynamic: author
Dynamic: author-email
Dynamic: classifier
Dynamic: description
Dynamic: description-content-type
Dynamic: home-page
Dynamic: keywords
Dynamic: license
Dynamic: provides-extra
Dynamic: requires-dist
Dynamic: requires-python
Dynamic: summary
